quake/__init__.py
quake/cli.py
quake/cli_domain.py
quake/cli_host.py
quake/cli_info.py
quake/cli_init.py
quake/quake.py
quake-1.0.2.dist-info/LICENSE
quake-1.0.2.dist-info/METADATA
quake-1.0.2.dist-info/WHEEL
quake-1.0.2.dist-info/entry_points.txt
quake-1.0.2.dist-info/top_level.txt
quake-1.0.2.dist-info/RECORD
