Metadata-Version: 2.1
Name: quake
Version: 1.0.2
Summary: quake.360.cn的API库
Home-page: https://gitee.com/kin9-0rz/quake
Author: King Orz
Author-email: kin9-0rz@outlook.com
License: MIT license
Keywords: quake
Platform: UNKNOWN
Classifier: Development Status :: 2 - Pre-Alpha
Classifier: Intended Audience :: Developers
Classifier: License :: OSI Approved :: MIT License
Classifier: Natural Language :: English
Classifier: Programming Language :: Python :: 3
Classifier: Programming Language :: Python :: 3.5
Classifier: Programming Language :: Python :: 3.6
Classifier: Programming Language :: Python :: 3.7
Classifier: Programming Language :: Python :: 3.8
Requires-Python: >=3.5
Requires-Dist: Click (>=7.0)
Requires-Dist: toml
Requires-Dist: requests
